{
  "items": [
    {
      "id": 1,
      "title": "欢迎来到我的网站",
      "content": "<p>这是我的<strong>第一篇文章</strong>。网站刚刚上线，后续会持续更新技术文章、教程和资源分享。</p><p>感谢访问！ 🚀</p>",
      "excerpt": "网站上线第一篇文章，介绍本站内容和计划",
      "cover": "",
      "tags": [
        "公告"
      ],
      "status": "published",
      "author_id": 1,
      "created_at": "2026-06-22T13:32:10.984Z",
      "updated_at": "2026-06-22T13:32:10.984Z"
    },
    {
      "id": 2,
      "title": "如何高效学习一门新技术",
      "content": "<h2>5 步学习法</h2><ol><li><strong>明确目标</strong> — 搞清楚 Why/What/How</li><li><strong>看官方文档</strong> — 第一手信息来源</li><li><strong>最小可行项目</strong> — 边做边学</li><li><strong>教给别人</strong> — 费曼学习法</li><li><strong>持续迭代</strong> — 小步快跑</li></ol>",
      "excerpt": "在信息爆炸的时代，掌握高效学习方法比掌握具体技术更重要",
      "cover": "",
      "tags": [
        "学习方法",
        "效率"
      ],
      "status": "published",
      "author_id": 1,
      "created_at": "2026-06-22T13:32:10.985Z",
      "updated_at": "2026-06-22T13:32:10.985Z"
    }
  ],
  "nextId": 3
}